cli.py
boa/__init__.py
boa/boa.py
boa/settings.py
boa/templates.py
pboa-0.0.3a0.dist-info/METADATA
pboa-0.0.3a0.dist-info/WHEEL
pboa-0.0.3a0.dist-info/entry_points.txt
pboa-0.0.3a0.dist-info/top_level.txt
pboa-0.0.3a0.dist-info/RECORD
