Metadata-Version: 2.1
Name: pboa
Version: 0.0.3a0
Summary: UNKNOWN
Home-page: https://github.com/kentaasvang/boa
Author: Kent Martin Åsvang
Author-email: kentaasvang@gmail.com
License: UNKNOWN
Platform: UNKNOWN
Classifier: Programming Language :: Python :: 3.8
Classifier: Environment :: Console
Classifier: Operating System :: OS Independent
Requires-Python: >=3.8
Requires-Dist: Click
